pokers-0.1.2.dist-info/METADATA
pokers-0.1.2.dist-info/WHEEL
pokers/__init__.py
pokers/__init__.pyi
pokers/py.typed
pokers/pokers.pypy310-pp73-aarch64-linux-gnu.so
pokers-0.1.2.dist-info/RECORD
