Metadata-Version: 2.1
Name: pokers
Version: 0.1.2
Classifier: Programming Language :: Rust
Classifier: Programming Language :: Python :: Implementation :: CPython
Classifier: Programming Language :: Python :: Implementation :: PyPy
Requires-Dist: pytest ; extra == 'dev'
Requires-Dist: black ; extra == 'dev'
Requires-Dist: mypy ; extra == 'dev'
Requires-Dist: ruff ; extra == 'dev'
Provides-Extra: dev
Summary: Embarrassingly simple No Limit Texas Holdem environment for RL
Keywords: poker,reinforcement learning
Requires-Python: >=3.7
